aioaseko/__init__.py
aioaseko/exceptions.py
aioaseko/mobile.py
aioaseko/py.typed
aioaseko/unit.py
aioaseko/variable.py
aioaseko/web.py
aioaseko-0.2.0.dist-info/COPYING
aioaseko-0.2.0.dist-info/COPYING.LESSER
aioaseko-0.2.0.dist-info/METADATA
aioaseko-0.2.0.dist-info/WHEEL
aioaseko-0.2.0.dist-info/top_level.txt
aioaseko-0.2.0.dist-info/RECORD
