Metadata-Version: 2.1
Name: aioaseko
Version: 0.2.0
Summary: Async Python package for the Aseko Pool Live API
Home-page: https://github.com/milanmeu/aioaseko
Author: Milan Meulemans
Author-email: milan.meulemans@live.be
License: LGPLv3+
Project-URL: Say Thanks!, https://saythanks.io/to/milan.meulemans@live.be
Project-URL: Bug Tracker, https://github.com/milanmeu/aioaseko/issues
Project-URL: Source Code, https://github.com/milanmeu/aioaseko
Project-URL: Documentation, https://github.com/milanmeu/aioaseko/blob/main/README.md
Keywords: aseko pool live api asin aqua
Classifier: Programming Language :: Python :: 3
Classifier: License :: OSI Approved :: GNU Lesser General Public License v3 or later (LGPLv3+)
Classifier: Operating System :: OS Independent
Classifier: Development Status :: 4 - Beta
Classifier: Intended Audience :: Developers
Classifier: Natural Language :: English
Classifier: Topic :: Home Automation
Classifier: Typing :: Typed
Requires-Python: >=3.8
License-File: COPYING
License-File: COPYING.LESSER
Requires-Dist: aiohttp
Requires-Dist: pyjwt
